{
"SSH_INFO":{
	"USERNAME":"jbergquist",
	"KEY_PATH":"C:/Users/jake/.ssh/sci_compute",
	"JUMP_HOST":"shell.sci.utah.edu",
	"JUMP_PORT":"5522"
},
"LOCAL_INFO":{
	"BASE_PATH":"../",
	"LOG_PATH":"../logs/"
},
"NODES":{
	"wall-e":{
	"HOSTNAME":"wall-e.sci.utah.edu",
	"INTERP_PATH":"/uu/sci.utah.edu/projects/CEG/Tools/pythonEnvs/systemMonitor/bin/python",
	"LABEL":"wall-e",
	"BASE_PATH":"/uu/sci.utah.edu/projects/CEG/Tools/ComputeDash/ComputeDash/",
	"LOG_PATH":"../logs/",
	"SCRIP_PATH":"remoteQuery/remote_wrapper.py",
	"LOG_FILE":"wall-e.stats"
	},
	"cibcgpu1":{
	"HOSTNAME":"cibcgpu1.sci.utah.edu",
	"INTERP_PATH":"/uu/sci.utah.edu/projects/CEG/Tools/pythonEnvs/systemMonitor/bin/python",
	"LABEL":"cibcgpu1",
	"BASE_PATH":"/uu/sci.utah.edu/projects/CEG/Tools/ComputeDash/ComputeDash/",
	"LOG_PATH":"../logs/",
	"SCRIP_PATH":"remoteQuery/remote_wrapper.py",
	"LOG_FILE":"cibcgpu1.stats"
	},
	"cibcgpu2":{
	"HOSTNAME":"cibcgpu2.sci.utah.edu",
	"INTERP_PATH":"/uu/sci.utah.edu/projects/CEG/Tools/pythonEnvs/systemMonitor/bin/python",
	"LABEL":"cibcgpu2",
	"BASE_PATH":"/uu/sci.utah.edu/projects/CEG/Tools/ComputeDash/ComputeDash/",
	"LOG_PATH":"../logs/",
	"SCRIP_PATH":"remoteQuery/remote_wrapper.py",
	"LOG_FILE":"cibcgpu2.stats"
	},
	"cibcgpu3":{
	"HOSTNAME":"cibcgpu3.sci.utah.edu",
	"INTERP_PATH":"/uu/sci.utah.edu/projects/CEG/Tools/pythonEnvs/systemMonitor/bin/python",
	"LABEL":"cibcgpu3",
	"BASE_PATH":"/uu/sci.utah.edu/projects/CEG/Tools/ComputeDash/ComputeDash/",
	"LOG_PATH":"../logs/",
	"SCRIP_PATH":"remoteQuery/remote_wrapper.py",
	"LOG_FILE":"cibcgpu3.stats"
	},
	"cibcgpu4":{
	"HOSTNAME":"cibcgpu4.sci.utah.edu",
	"INTERP_PATH":"/uu/sci.utah.edu/projects/CEG/Tools/pythonEnvs/systemMonitor/bin/python",
	"LABEL":"cibcgpu4",
	"BASE_PATH":"/uu/sci.utah.edu/projects/CEG/Tools/ComputeDash/ComputeDash/",
	"LOG_PATH":"../logs/",
	"SCRIP_PATH":"remoteQuery/remote_wrapper.py",
	"LOG_FILE":"cibcgpu4.stats"
	},
	"zagreus":{
	"HOSTNAME":"zagreus.sci.utah.edu",
	"INTERP_PATH":"/uu/sci.utah.edu/projects/CEG/Tools/pythonEnvs/systemMonitor/bin/python",
	"LABEL":"zagreus",
	"BASE_PATH":"/uu/sci.utah.edu/projects/CEG/Tools/ComputeDash/ComputeDash/",
	"LOG_PATH":"../logs/",
	"SCRIP_PATH":"remoteQuery/remote_wrapper.py",
	"LOG_FILE":"zagreus.stats"
	},
	"cibcsm1":{
	"HOSTNAME":"cibcsm1.sci.utah.edu",
	"INTERP_PATH":"/uu/sci.utah.edu/projects/CEG/Tools/pythonEnvs/systemMonitor/bin/python",
	"LABEL":"cibcsm1",
	"BASE_PATH":"/uu/sci.utah.edu/projects/CEG/Tools/ComputeDash/ComputeDash/",
	"LOG_PATH":"../logs/",
	"SCRIP_PATH":"remoteQuery/remote_wrapper.py",
	"LOG_FILE":"cibcsm1.stats"
	},
	"cibcsm2":{
	"HOSTNAME":"cibcsm2.sci.utah.edu",
	"INTERP_PATH":"/uu/sci.utah.edu/projects/CEG/Tools/pythonEnvs/systemMonitor/bin/python",
	"LABEL":"cibcsm2",
	"BASE_PATH":"/uu/sci.utah.edu/projects/CEG/Tools/ComputeDash/ComputeDash/",
	"LOG_PATH":"../logs/",
	"SCRIP_PATH":"remoteQuery/remote_wrapper.py",
	"LOG_FILE":"cibcsm2.stats"
	},
	"cibcsm3":{
	"HOSTNAME":"cibcsm3.sci.utah.edu",
	"INTERP_PATH":"/uu/sci.utah.edu/projects/CEG/Tools/pythonEnvs/systemMonitor/bin/python",
	"LABEL":"cibcsm3",
	"BASE_PATH":"/uu/sci.utah.edu/projects/CEG/Tools/ComputeDash/ComputeDash/",
	"LOG_PATH":"../logs/",
	"SCRIP_PATH":"remoteQuery/remote_wrapper.py",
	"LOG_FILE":"cibcsm3.stats"
	},
	"cibcsm4":{
	"HOSTNAME":"cibcsm4.sci.utah.edu",
	"INTERP_PATH":"/uu/sci.utah.edu/projects/CEG/Tools/pythonEnvs/systemMonitor/bin/python",
	"LABEL":"cibcsm4",
	"BASE_PATH":"/uu/sci.utah.edu/projects/CEG/Tools/ComputeDash/ComputeDash/",
	"LOG_PATH":"../logs/",
	"SCRIP_PATH":"remoteQuery/remote_wrapper.py",
	"LOG_FILE":"cibcsm4.stats"
	}
}
}